nimue/__init__.py
nimue/callback.py
nimue/nimue.py
nimue-0.0.3.dist-info/LICENSE
nimue-0.0.3.dist-info/METADATA
nimue-0.0.3.dist-info/WHEEL
nimue-0.0.3.dist-info/top_level.txt
nimue-0.0.3.dist-info/RECORD
